common_utils/__init__.py
common_utils/async_task_processor.py
common_utils/file_utils.py
common_utils/http_wrapper.py
common_utils/image_downloader.py
common_utils/shell_scripts_handler.py
common_utils/task_completion_source.py
common_utils/wake_machine.py
common_utils/shell_scripts/__init__.py
common_utils/shell_scripts/kill-process-at-port.sh
common_utils/shell_scripts/start-adb-app.sh
common_utils/shell_scripts/start-firefox-at-url.sh
common_utils/shell_scripts/start-npm-at-path.sh
common_utils/shell_scripts/start-virtual-machine.sh
thetemani_common_utils-0.1.7.dist-info/licenses/LICENSE
thetemani_common_utils-0.1.7.dist-info/METADATA
thetemani_common_utils-0.1.7.dist-info/WHEEL
thetemani_common_utils-0.1.7.dist-info/top_level.txt
thetemani_common_utils-0.1.7.dist-info/RECORD
