Metadata-Version: 2.4
Name: thetemani-common-utils
Version: 0.1.7
Summary: A collection of common utility functions and scripts
Author: Omer Hadad
License: MIT
Project-URL: Homepage, https://github.com/Omer-hadad-s-Projects/common
Project-URL: Bug Reports, https://github.com/Omer-hadad-s-Projects/common/issues
Project-URL: Source, https://github.com/Omer-hadad-s-Projects/common
Classifier: Programming Language :: Python :: 3
Classifier: Operating System :: OS Independent
Classifier: Development Status :: 3 - Alpha
Classifier: Intended Audience :: Developers
Classifier: Topic :: Software Development :: Libraries :: Python Modules
Requires-Python: >=3.6
License-File: LICENSE
Requires-Dist: aiohappyeyeballs==2.4.2
Requires-Dist: aiohttp==3.10.7
Requires-Dist: aiosignal==1.3.1
Requires-Dist: attrs==24.2.0
Requires-Dist: frozenlist==1.4.1
Requires-Dist: idna==3.10
Requires-Dist: multidict==6.1.0
Requires-Dist: yarl==1.13.1
Dynamic: author
Dynamic: classifier
Dynamic: description
Dynamic: description-content-type
Dynamic: license
Dynamic: license-file
Dynamic: project-url
Dynamic: requires-dist
Dynamic: requires-python
Dynamic: summary
